azure/communication/messages/__init__.py
azure/communication/messages/_api_versions.py
azure/communication/messages/_client.py
azure/communication/messages/_configuration.py
azure/communication/messages/_model_base.py
azure/communication/messages/_patch.py
azure/communication/messages/_serialization.py
azure/communication/messages/_types.py
azure/communication/messages/_vendor.py
azure/communication/messages/_version.py
azure/communication/messages/py.typed
azure/communication/messages/_operations/__init__.py
azure/communication/messages/_operations/_operations.py
azure/communication/messages/_operations/_patch.py
azure/communication/messages/_shared/__init__.py
azure/communication/messages/_shared/auth_policy_utils.py
azure/communication/messages/_shared/models.py
azure/communication/messages/_shared/policy.py
azure/communication/messages/_shared/user_credential.py
azure/communication/messages/_shared/user_credential_async.py
azure/communication/messages/_shared/utils.py
azure/communication/messages/_shared/utils_async.py
azure/communication/messages/aio/__init__.py
azure/communication/messages/aio/_client.py
azure/communication/messages/aio/_configuration.py
azure/communication/messages/aio/_patch.py
azure/communication/messages/aio/_vendor.py
azure/communication/messages/aio/_operations/__init__.py
azure/communication/messages/aio/_operations/_operations.py
azure/communication/messages/aio/_operations/_patch.py
azure/communication/messages/models/__init__.py
azure/communication/messages/models/_enums.py
azure/communication/messages/models/_models.py
azure/communication/messages/models/_patch.py
azure_communication_messages-1.1.0.dist-info/LICENSE
azure_communication_messages-1.1.0.dist-info/METADATA
azure_communication_messages-1.1.0.dist-info/WHEEL
azure_communication_messages-1.1.0.dist-info/top_level.txt
azure_communication_messages-1.1.0.dist-info/RECORD
